{
   "type": "entity",
   "mixins": "stonehearth:mixins:item_properties",
   "components": {
      "model_variants": {
         "default": {
            "models": [
               "file(defender_iron_spear.qb)"
            ]
         }
      },
      "effect_list": {
         "default": "stonehearth:effects:talisman_glow"
      },
      "stonehearth:promotion_talisman": {
         "job": "calltoarms:jobs:defender"
      }
   },
   "entity_data": {
      "stonehearth:net_worth": {
         "value_in_gold": 15,
         "rarity": "rare",
         "shop_info": {
            "buyable": true,
            "sellable": true,
            "shopkeeper_level": 1,
            "shopkeeper_type": "caravan"
         }
      },
      "stonehearth:catalog": {
         "display_name": "i18n(calltoarms:jobs.defender.defender_iron_spear.defender_iron_spear_talisman.display_name)",
         "description": "i18n(calltoarms:jobs.defender.defender_iron_spear.defender_iron_spear_talisman.description)",
         "icon": "file(defender_iron_spear.png)",
         "is_item": true,
         "category": "tools",
         "material_tags": "stockpile_tool"
      }
   }
}